ExifReader-0.1.1.data/scripts/EXIF.py
exifreader/__init__.py
exifreader/classes.py
exifreader/exif_log.py
exifreader/heic.py
exifreader/utils.py
exifreader/tags/__init__.py
exifreader/tags/exif.py
exifreader/tags/makernote/__init__.py
exifreader/tags/makernote/apple.py
exifreader/tags/makernote/canon.py
exifreader/tags/makernote/casio.py
exifreader/tags/makernote/fujifilm.py
exifreader/tags/makernote/nikon.py
exifreader/tags/makernote/olympus.py
ExifReader-0.1.1.dist-info/LICENSE.txt
ExifReader-0.1.1.dist-info/METADATA
ExifReader-0.1.1.dist-info/WHEEL
ExifReader-0.1.1.dist-info/top_level.txt
ExifReader-0.1.1.dist-info/RECORD
