Metadata-Version: 2.1
Name: ExifReader
Version: 0.1.1
Summary: Read Exif metadata from tiff and jpeg files.
Home-page: https://gitlab.com/Cyb3r-Jak3/exifreader
Author: Cyb3r Jak3
Author-email: jake@jwhite.network
License: BSD
Project-URL: Issues, https://gitlab.com/Cyb3r-Jak3/ExifReader/issues
Project-URL: Source Code, https://gitlab.com/Cyb3r-Jak3/ExifReader/-/tree/publish
Project-URL: CI, https://gitlab.com/Cyb3r-Jak3/ExifReader/pipelines
Project-URL: Releases, https://github.com/Cyb3r-Jak3/ExifReader
Keywords: exif image metadata photo
Platform: UNKNOWN
Classifier: Development Status :: 5 - Production/Stable
Classifier: Environment :: Console
Classifier: Intended Audience :: Developers
Classifier: Intended Audience :: End Users/Desktop
Classifier: License :: OSI Approved :: BSD License
Classifier: Operating System :: OS Independent
Classifier: Programming Language :: Python :: 3.4
Classifier: Programming Language :: Python :: 3.5
Classifier: Programming Language :: Python :: 3.6
Classifier: Programming Language :: Python :: 3.7
Classifier: Topic :: Utilities
Requires-Python: >=3.4
Requires-Dist: defusedxml (>=0.6.0)
